{
  "event": "ANNOTATION_CREATED",
  "job_id": "1770031967",
  "data": {
    "annotation": {
      "id": 21,
      "result": [
        {
          "value": {
            "choices": [
              "Business"
            ]
          },
          "id": "zTCTB1g1tv",
          "from_name": "label",
          "to_name": "text",
          "type": "choices",
          "origin": "prediction-changed"
        }
      ],
      "was_cancelled": false,
      "ground_truth": false,
      "created_at": "2026-02-02T11:32:46.644516Z",
      "updated_at": "2026-02-02T11:32:46.644516Z",
      "draft_created_at": null,
      "lead_time": 12.998,
      "prediction": {},
      "result_count": 1,
      "unique_id": "900a1b09-a578-4fdd-b07d-e58bfe205998",
      "import_id": null,
      "last_action": null,
      "bulk_created": false,
      "task": 42,
      "project": 1,
      "completed_by": 1,
      "updated_by": 1,
      "parent_prediction": 24,
      "parent_annotation": null,
      "last_created_by": null
    },
    "project": {
      "id": 1,
      "task_number": 20,
      "finished_task_number": 2,
      "total_predictions_number": 2,
      "total_annotations_number": 2,
      "num_tasks_with_annotations": 2,
      "useful_annotation_number": 2,
      "ground_truth_number": 0,
      "skipped_annotations_number": 0,
      "title": "New Project #1",
      "description": "",
      "label_config": "<View>\n  <Text name=\"text\" value=\"$text\"/>\n  <View style=\"box-shadow: 2px 2px 5px #999; padding: 20px; margin-top: 2em; border-radius: 5px;\">\n    <Header value=\"Choose Topic:\"/>\n    <Choices name=\"label\" toName=\"text\" choice=\"single\" showInLine=\"true\">\n      <Choice value=\"World\"/>\n      <Choice value=\"Sports\"/>\n      <Choice value=\"Business\"/>\n      <Choice value=\"Sci/Tech\"/>\n    </Choices>\n  </View>\n</View>",
      "parsed_label_config": {
        "label": {
          "type": "Choices",
          "to_name": [
            "text"
          ],
          "inputs": [
            {
              "type": "Text",
              "valueType": null,
              "value": "text"
            }
          ],
          "labels": [
            "World",
            "Sports",
            "Business",
            "Sci/Tech"
          ],
          "labels_attrs": {
            "World": {
              "value": "World"
            },
            "Sports": {
              "value": "Sports"
            },
            "Business": {
              "value": "Business"
            },
            "Sci/Tech": {
              "value": "Sci/Tech"
            }
          }
        }
      },
      "label_config_hash": 2902683155182968561,
      "expert_instruction": "",
      "show_instruction": false,
      "show_skip_button": true,
      "enable_empty_annotation": true,
      "reveal_preannotations_interactively": false,
      "show_annotation_history": false,
      "show_collab_predictions": true,
      "evaluate_predictions_automatically": false,
      "token": "1Q4eL3QvWOOiF4sqWObtkUMb6AuKRAM4o0ZFOlsI",
      "result_count": 0,
      "color": "#FFFFFF",
      "maximum_annotations": 1,
      "min_annotations_to_start_training": 0,
      "control_weights": {
        "label": {
          "overall": 1.0,
          "type": "Choices",
          "labels": {
            "World": 1.0,
            "Sports": 1.0,
            "Business": 1.0,
            "Sci/Tech": 1.0
          }
        }
      },
      "model_version": "ML Model",
      "data_types": {
        "text": "Text"
      },
      "is_draft": false,
      "is_published": false,
      "created_at": "2025-08-02T14:01:04.532362Z",
      "updated_at": "2026-02-02T11:30:42.823172Z",
      "sampling": "Sequential sampling",
      "skip_queue": "REQUEUE_FOR_OTHERS",
      "show_ground_truth_first": false,
      "show_overlap_first": false,
      "overlap_cohort_percentage": 100,
      "task_data_login": null,
      "task_data_password": null,
      "pinned_at": null,
      "custom_task_lock_ttl": null,
      "organization": 1,
      "created_by": 1
    },
    "task": {
      "id": 42,
      "data": {
        "text": "Carlyle Looks Toward Commercial Aerospace (Reuters) Reuters - Private investment firm Carlyle Group,\nwhich has a reputation for making well-timed and occasionally\ncontroversial plays in the defense industry, has quietly placed\nits bets on another part of the aerospace market."
      },
      "meta": {},
      "created_at": "2026-02-01T15:44:54.876241Z",
      "updated_at": "2026-02-02T11:32:46.707376Z",
      "is_labeled": true,
      "overlap": 1,
      "inner_id": 2,
      "total_annotations": 1,
      "cancelled_annotations": 0,
      "total_predictions": 1,
      "comment_count": 0,
      "unresolved_comment_count": 0,
      "last_comment_updated_at": null,
      "project": 1,
      "updated_by": 1,
      "file_upload": 3,
      "comment_authors": []
    }
  }
}